muxes/mux_4_to_1/mux_4_to_1.sv
module mux_4_to_1
#(
	parameter   WIDTH = 32
	
)

(
input      [WIDTH-1:0]     i_data0,
input      [WIDTH-1:0]     i_data1,
input      [WIDTH-1:0]     i_data2,
input      [WIDTH-1:0]     i_data3,
input      [1:0] i_sel,
output reg [WIDTH-1:0]     o_data
);


always@*
	begin
		case(i_sel)
			2'b00 : o_data = i_data0;
			2'b01 : o_data = i_data1;
			2'b10 : o_data = i_data2;
			2'b11 : o_data = i_data3;
		endcase
	end	
endmodule

muxes/mux_4_to_1/tb_mux_4_to_1.sv
module tb_mux_4_to_1;
parameter WIDTH = 32;
reg  [WIDTH-1:0]     i_data0;
reg  [WIDTH-1:0]     i_data1;
reg  [WIDTH-1:0]     i_data2;
reg  [WIDTH-1:0]     i_data3;
reg  [1:0]           i_sel;
wire [WIDTH-1:0]     o_data;


mux_4_to_1
#(
	.WIDTH		        	(WIDTH	    )
)

inst_mux_4_to_1
(
	.i_data0(i_data0),
	.i_data1(i_data1),
	.i_data2(i_data2),
	.i_data3(i_data3),
	.i_sel(i_sel),
	.o_data(o_data)
);

initial 
begin
    $dumpfile("wave.vcd");
	$dumpvars(0, tb_mux_4_to_1);	

	repeat (10)
		begin	
			stimulus();
		end
end

task stimulus();
	begin
		i_data0 = $urandom_range(0, 31);
		i_data1 = $urandom_range(0, 31);
		i_data2 = $urandom_range(0, 31);
		i_data3 = $urandom_range(0, 31);
		i_sel = $urandom_range(0,3);#5;
	end
endtask

initial begin
	#500 $finish;
end

endmodule

muxes/mux_4_to_1/wave.vcd
$date
	Mon Jul  3 16:35:42 2023
$end
$version
	Icarus Verilog
$end
$timescale
	1s
$end
$scope module tb_mux_4_to_1 $end
$var wire 32 ! o_data [31:0] $end
$var reg 32 " i_data0 [31:0] $end
$var reg 32 # i_data1 [31:0] $end
$var reg 32 $ i_data2 [31:0] $end
$var reg 32 % i_data3 [31:0] $end
$var reg 2 & i_sel [1:0] $end
$scope module inst_mux_4_to_1 $end
$var wire 32 ' i_data0 [31:0] $end
$var wire 32 ( i_data1 [31:0] $end
$var wire 32 ) i_data2 [31:0] $end
$var wire 32 * i_data3 [31:0] $end
$var wire 2 + i_sel [1:0] $end
$var reg 32 , o_data [31:0] $end
$upscope $end
$scope task stimulus $end
$upscope $end
$upscope $end
$enddefinitions $end
#0
$dumpvars
b0 ,
b10 +
b110 *
b0 )
b1000 (
b10010 '
b10 &
b110 %
b0 $
b1000 #
b10010 "
b0 !
$end
#5
b1 !
b1 ,
b10000 %
b10000 *
b1 $
b1 )
b110 #
b110 (
b11000 "
b11000 '
#10
b11000 !
b11000 ,
b11 &
b11 +
b11000 %
b11000 *
b11110 $
b11110 )
b10011 #
b10011 (
b10111 "
b10111 '
#15
b1100 !
b1100 ,
b0 &
b0 +
b11110 %
b11110 *
b1010 $
b1010 )
b1100 #
b1100 (
b1100 "
b1100 '
#20
b11000 !
b11000 ,
b1 &
b1 +
b1100 %
b1100 *
b11111 $
b11111 )
b11000 #
b11000 (
b1 "
b1 '
#25
b1100 !
b1100 ,
b0 &
b0 +
b10 %
b10 *
b1011 $
b1011 )
b10101 #
b10101 (
b1100 "
b1100 '
#30
b10010 !
b10010 ,
b11 &
b11 +
b10010 %
b10010 *
b1000 $
b1000 )
b10000 #
b10000 (
b110 "
b110 '
#35
b1001 !
b1001 ,
b0 &
b0 +
b0 %
b0 *
b1 $
b1 )
b1001 #
b1001 (
b1001 "
b1001 '
#40
b0 !
b0 ,
b10 &
b10 +
b1010 %
b1010 *
b0 $
b0 )
b1101 #
b1101 (
b10110 "
b10110 '
#45
b1100 !
b1100 ,
b0 &
b0 +
b1100 %
b1100 *
b10000 $
b10000 )
b10010 #
b10010 (
b1100 "
b1100 '
