decoder/SixToSixtyFourDecoder.v
module SixToSixtyFourDecoder (
    input [5:0] select,
    output reg [13:0] segments
);

    always @* begin
		case(select)
		6'd00: segments = 14'b1111110_1111110;
		6'd01: segments = 14'b1111110_0110000;
		6'd02: segments = 14'b1111110_1101101;
		6'd03: segments = 14'b1111110_1111001;
		6'd04: segments = 14'b1111110_0110011;
		6'd05: segments = 14'b1111110_1011011;
		6'd06: segments = 14'b1111110_1011111;
		6'd07: segments = 14'b1111110_1110000;
		6'd08: segments = 14'b1111110_1111111;
		6'd09: segments = 14'b1111110_1111011;
		
		6'd10: segments = 14'b0110000_1111110;
		6'd11: segments = 14'b0110000_0110000;
		6'd12: segments = 14'b0110000_1101101;
		6'd13: segments = 14'b0110000_1111001;
		6'd14: segments = 14'b0110000_0110011;
		6'd15: segments = 14'b0110000_1011011;
		6'd16: segments = 14'b0110000_1011111;
		6'd17: segments = 14'b0110000_1110000;
		6'd18: segments = 14'b0110000_1111111;
		6'd19: segments = 14'b0110000_1111011;
		
		6'd20: segments = 14'b1101101_1111110;
		6'd21: segments = 14'b1101101_0110000;
		6'd22: segments = 14'b1101101_1101101;
		6'd23: segments = 14'b1101101_1111001;
		6'd24: segments = 14'b1101101_0110011;
		6'd25: segments = 14'b1101101_1011011;
		6'd26: segments = 14'b1101101_1011111;
		6'd27: segments = 14'b1101101_1110000;
		6'd28: segments = 14'b1101101_1111111;
		6'd29: segments = 14'b1101101_1111011;
		
		6'd30: segments = 14'b1111001_1111110;
		6'd31: segments = 14'b1111001_0110000;
		6'd32: segments = 14'b1111001_1101101;
		6'd33: segments = 14'b1111001_1111001;
		6'd34: segments = 14'b1111001_0110011;
		6'd35: segments = 14'b1111001_1011011;
		6'd36: segments = 14'b1111001_1011111;
		6'd37: segments = 14'b1111001_1110000;
		6'd38: segments = 14'b1111001_1111111;
		6'd39: segments = 14'b1111001_1111011;
	
		6'd40: segments = 14'b0110011_1111110;
		6'd41: segments = 14'b0110011_0110000;
		6'd42: segments = 14'b0110011_1101101;
		6'd43: segments = 14'b0110011_1111001;
		6'd44: segments = 14'b0110011_0110011;
		6'd45: segments = 14'b0110011_1011011;
		6'd46: segments = 14'b0110011_1011111;
		6'd47: segments = 14'b0110011_1110000;
		6'd48: segments = 14'b0110011_1111111;
		6'd49: segments = 14'b0110011_1111011;
		
		6'd50: segments = 14'b1011011_1111110;
		6'd51: segments = 14'b1011011_0110000;
		6'd52: segments = 14'b1011011_1101101;
		6'd53: segments = 14'b1011011_1111001;
		6'd54: segments = 14'b1011011_0110011;
		6'd55: segments = 14'b1011011_1011011;
		6'd56: segments = 14'b1011011_1011111;
		6'd57: segments = 14'b1011011_1110000;
		6'd58: segments = 14'b1011011_1111111;
		6'd59: segments = 14'b1011011_1111011;	
		endcase
	end

endmodule

decoder/SixToSixtyFourDecoder_TB.v
module SixToSixtyFourDecoder_TB;

    // Inputs
    reg [5:0] select;
    
    // Outputs
    wire [13:0] segments;

    // Instantiate the module
    SixToSixtyFourDecoder decoder (
        .select(select),
        .segments(segments)
    );
    
    // Stimulus generation
    initial begin
		$dumpfile("wave.vcd");
		$dumpvars(0,SixToSixtyFourDecoder_TB);
        
        // Test all possible inputs
        for (select = 0; select < 60; select = select + 1) begin
			$display("select = %d, segments = %b", select, segments);
            #10; // Wait for a few simulation time units
        end
        
		
		/*
		select = 0;
		#10;
		$display("select = %d, segments = %b", select, segments);
		select = 1;
		#10;
		$display("select = %d, segments = %b", select, segments);
		select = 2;
		#10;
		$display("select = %d, segments = %b", select, segments);
		select = 3;
		#10;
		$display("select = %d, segments = %b", select, segments);
		select = 4;
		#10;
		$display("select = %d, segments = %b", select, segments);
		select = 5;
		#10;
		$display("select = %d, segments = %b", select, segments);
		select = 6;
		#10;
		$display("select = %d, segments = %b", select, segments);
		select = 7;
		#10;
		$display("select = %d, segments = %b", select, segments);
		select = 8;
		#10;
		$display("select = %d, segments = %b", select, segments);
		select = 9;
		#10;
		$display("select = %d, segments = %b", select, segments);
		select = 10;
		#10;
		$display("select = %d, segments = %b", select, segments);
        $finish; // End simulation
		*/
    end

endmodule

decoder/wave.vcd
$date
	Wed Aug 23 10:41:12 2023
$end
$version
	Icarus Verilog
$end
$timescale
	1s
$end
$scope module SixToSixtyFourDecoder_TB $end
$var wire 14 ! segments [13:0] $end
$var reg 6 " select [5:0] $end
$scope module decoder $end
$var wire 6 # select [5:0] $end
$var reg 14 $ segments [13:0] $end
$upscope $end
$upscope $end
$enddefinitions $end
#0
$dumpvars
b11111101111110 $
b0 #
b0 "
b11111101111110 !
$end
#10
b11111100110000 !
b11111100110000 $
b1 "
b1 #
#20
b11111101101101 !
b11111101101101 $
b10 "
b10 #
#30
b11111101111001 !
b11111101111001 $
b11 "
b11 #
#40
b11111100110011 !
b11111100110011 $
b100 "
b100 #
#50
b11111101011011 !
b11111101011011 $
b101 "
b101 #
#60
b11111101011111 !
b11111101011111 $
b110 "
b110 #
#70
b11111101110000 !
b11111101110000 $
b111 "
b111 #
#80
b11111101111111 !
b11111101111111 $
b1000 "
b1000 #
#90
b11111101111011 !
b11111101111011 $
b1001 "
b1001 #
#100
b1100001111110 !
b1100001111110 $
b1010 "
b1010 #
#110
b1100000110000 !
b1100000110000 $
b1011 "
b1011 #
#120
b1100001101101 !
b1100001101101 $
b1100 "
b1100 #
#130
b1100001111001 !
b1100001111001 $
b1101 "
b1101 #
#140
b1100000110011 !
b1100000110011 $
b1110 "
b1110 #
#150
b1100001011011 !
b1100001011011 $
b1111 "
b1111 #
#160
b1100001011111 !
b1100001011111 $
b10000 "
b10000 #
#170
b1100001110000 !
b1100001110000 $
b10001 "
b10001 #
#180
b1100001111111 !
b1100001111111 $
b10010 "
b10010 #
#190
b1100001111011 !
b1100001111011 $
b10011 "
b10011 #
#200
b11011011111110 !
b11011011111110 $
b10100 "
b10100 #
#210
b11011010110000 !
b11011010110000 $
b10101 "
b10101 #
#220
b11011011101101 !
b11011011101101 $
b10110 "
b10110 #
#230
b11011011111001 !
b11011011111001 $
b10111 "
b10111 #
#240
b11011010110011 !
b11011010110011 $
b11000 "
b11000 #
#250
b11011011011011 !
b11011011011011 $
b11001 "
b11001 #
#260
b11011011011111 !
b11011011011111 $
b11010 "
b11010 #
#270
b11011011110000 !
b11011011110000 $
b11011 "
b11011 #
#280
b11011011111111 !
b11011011111111 $
b11100 "
b11100 #
#290
b11011011111011 !
b11011011111011 $
b11101 "
b11101 #
#300
b11110011111110 !
b11110011111110 $
b11110 "
b11110 #
#310
b11110010110000 !
b11110010110000 $
b11111 "
b11111 #
#320
b11110011101101 !
b11110011101101 $
b100000 "
b100000 #
#330
b11110011111001 !
b11110011111001 $
b100001 "
b100001 #
#340
b11110010110011 !
b11110010110011 $
b100010 "
b100010 #
#350
b11110011011011 !
b11110011011011 $
b100011 "
b100011 #
#360
b11110011011111 !
b11110011011111 $
b100100 "
b100100 #
#370
b11110011110000 !
b11110011110000 $
b100101 "
b100101 #
#380
b11110011111111 !
b11110011111111 $
b100110 "
b100110 #
#390
b11110011111011 !
b11110011111011 $
b100111 "
b100111 #
#400
b1100111111110 !
b1100111111110 $
b101000 "
b101000 #
#410
b1100110110000 !
b1100110110000 $
b101001 "
b101001 #
#420
b1100111101101 !
b1100111101101 $
b101010 "
b101010 #
#430
b1100111111001 !
b1100111111001 $
b101011 "
b101011 #
#440
b1100110110011 !
b1100110110011 $
b101100 "
b101100 #
#450
b1100111011011 !
b1100111011011 $
b101101 "
b101101 #
#460
b1100111011111 !
b1100111011111 $
b101110 "
b101110 #
#470
b1100111110000 !
b1100111110000 $
b101111 "
b101111 #
#480
b1100111111111 !
b1100111111111 $
b110000 "
b110000 #
#490
b1100111111011 !
b1100111111011 $
b110001 "
b110001 #
#500
b10110111111110 !
b10110111111110 $
b110010 "
b110010 #
#510
b10110110110000 !
b10110110110000 $
b110011 "
b110011 #
#520
b10110111101101 !
b10110111101101 $
b110100 "
b110100 #
#530
b10110111111001 !
b10110111111001 $
b110101 "
b110101 #
#540
b10110110110011 !
b10110110110011 $
b110110 "
b110110 #
#550
b10110111011011 !
b10110111011011 $
b110111 "
b110111 #
#560
b10110111011111 !
b10110111011111 $
b111000 "
b111000 #
#570
b10110111110000 !
b10110111110000 $
b111001 "
b111001 #
#580
b10110111111111 !
b10110111111111 $
b111010 "
b111010 #
#590
b10110111111011 !
b10110111111011 $
b111011 "
b111011 #
#600
b111100 "
b111100 #
